pyprose/__init__.py
pyprose/vignette/HeLa_DDA_sample.pkl
pyprose/vignette/klijn_panel_spearman.csv.gz
pyprose-1.0.0.dist-info/LICENSE
pyprose-1.0.0.dist-info/METADATA
pyprose-1.0.0.dist-info/WHEEL
pyprose-1.0.0.dist-info/top_level.txt
pyprose-1.0.0.dist-info/RECORD
